{
  "categories": [
    {
      "id": "2",
      "title": "Хобби"
    },
    {
      "id": "oQkY14c_-rFKqa4aRgllX",
      "title": "title123222"
    },
    {
      "id": "5nZY0PNVvVxuTHmUmms5w",
      "title": "ewgewhewbew"
    },
    {
      "id": "eXKaQqs7n7SJ4QCfqRWsY",
      "title": "y55j64"
    },
    {
      "id": "QVV4UJ88caMrYpmybc5sc",
      "title": "hgewhtrre"
    }
  ],
  "todos": [
    {
      "id": "wPglSUlBk3SF3gewrgewghIhwN_",
      "text": "читать мангу",
      "categoryId": "2"
    },
    {
      "id": "sz3s3C71enBCqaPMdSdTN",
      "text": "wegewgerw",
      "categoryId": "oQkY14c_-rFKqa4aRgllX"
    },
    {
      "id": "zC5H4Q6sJ9W2_R55OGIp2",
      "text": "ewgewwe",
      "categoryId": "oQkY14c_-rFKqa4aRgllX"
    },
    {
      "id": "99JnQiIAsRrcMyUCmbQPU",
      "text": "hello tyjrtjrtutsbresbkuytty",
      "categoryId": "oQkY14c_-rFKqa4aRgllX"
    },
    {
      "id": "heO8NsQd_xvzRDDMQYCf2",
      "text": "ewrgewrgew",
      "categoryId": "5nZY0PNVvVxuTHmUmms5w"
    },
    {
      "id": "YB6oQpWAEKX2eLmB3bGUx",
      "text": "ewgerwgg",
      "categoryId": "5nZY0PNVvVxuTHmUmms5w"
    },
    {
      "id": "Zcdy9xzcsV3ABUtWSOonx",
      "text": "ewgewrg",
      "categoryId": "5nZY0PNVvVxuTHmUmms5w"
    },
    {
      "id": "A1UB5JnxXu3cMBjuVIpqF",
      "text": "test1234",
      "categoryId": "oQkY14c_-rFKqa4aRgllX"
    },
    {
      "id": "MZ3EmTMp1gHjy-W1sbFq1",
      "text": "test",
      "categoryId": "oQkY14c_-rFKqa4aRgllX"
    }
  ]
}